README.md
setup.py
src/protodicts.py
src/protodicts.egg-info/PKG-INFO
src/protodicts.egg-info/SOURCES.txt
src/protodicts.egg-info/dependency_links.txt
src/protodicts.egg-info/requires.txt
src/protodicts.egg-info/top_level.txt