Metadata-Version: 1.1
Name: protodicts
Version: 1.1.1
Summary: a small Python library for 2 ways conversion between dicts and protocol buffers.
Home-page: https://github.com/alexyvassili/protodicts
Author: Eugene Van den Bulke
Author-email: eugene.vandenbulke@gmail.com
License: Public Domain
Keywords: protobuf,dict
Platform: UNKNOWN
Classifier: Programming Language :: Python
Classifier: Programming Language :: Python :: 2
Classifier: Programming Language :: Python :: 3
Classifier: Development Status :: 5 - Production/Stable
Classifier: Intended Audience :: Developers
Classifier: License :: Public Domain
Classifier: Operating System :: OS Independent
Classifier: Topic :: Software Development :: Libraries :: Python Modules
